pyspectrafuse/__init__.py
pyspectrafuse/pyspectrafuse_cli.py
pyspectrafuse/cluster_parquet_combine/__init__.py
pyspectrafuse/cluster_parquet_combine/cluster_res_handler.py
pyspectrafuse/cluster_parquet_combine/combine_cluster_and_parquet.py
pyspectrafuse/commands/__init__.py
pyspectrafuse/commands/quantmsio2mgf.py
pyspectrafuse/commands/spectrum2msp.py
pyspectrafuse/common/__init__.py
pyspectrafuse/common/constant.py
pyspectrafuse/common/msp_utils.py
pyspectrafuse/common/parquet_utils.py
pyspectrafuse/common/sdrf_utils.py
pyspectrafuse/consensus_strategy/__init__.py
pyspectrafuse/consensus_strategy/average_spectrum_strategy.py
pyspectrafuse/consensus_strategy/best_spetrum_strategy.py
pyspectrafuse/consensus_strategy/binning_strategy.py
pyspectrafuse/consensus_strategy/consensus_strategy_base.py
pyspectrafuse/consensus_strategy/metrics.py
pyspectrafuse/consensus_strategy/most_similar_strategy.py
pyspectrafuse/mgf_convert/__init__.py
pyspectrafuse/mgf_convert/parquet2mgf.py
pyspectrafuse-0.0.2.data/data/LICENSE
pyspectrafuse-0.0.2.dist-info/licenses/LICENSE
pyspectrafuse-0.0.2.dist-info/METADATA
pyspectrafuse-0.0.2.dist-info/WHEEL
pyspectrafuse-0.0.2.dist-info/entry_points.txt
pyspectrafuse-0.0.2.dist-info/top_level.txt
pyspectrafuse-0.0.2.dist-info/RECORD
