Metadata-Version: 2.4
Name: pyspectrafuse
Version: 0.0.2
Summary: Python library with utility scripts for spectrafuse pipeline
Home-page: https://github.com/bigbio/pyspectrafuse
Author: BigBio Team
Author-email: BigBio Team <ypriverol@gmail.com>
License: Apache-2.0
Project-URL: Homepage, https://github.com/bigbio/pyspectrafuse
Keywords: python,proteomics,quantms,cluster
Platform: any
Classifier: Programming Language :: Python :: 3
Classifier: License :: OSI Approved :: Apache Software License
Classifier: Operating System :: OS Independent
Classifier: Topic :: Scientific/Engineering :: Bio-Informatics
Requires-Python: >=3.8
License-File: LICENSE
Requires-Dist: Click>=8.3.1
Requires-Dist: numpy>=2.3.5
Requires-Dist: pandas>=2.3.3
Requires-Dist: pathlib>=1.0.1
Requires-Dist: pyarrow>=22.0.0
Requires-Dist: pyteomics>=4.7.5
Requires-Dist: spectrum_utils>=0.5.0
Dynamic: author
Dynamic: home-page
Dynamic: license-file
Dynamic: platform
Dynamic: requires-python
